LICENSE
README.md
setup.cfg
setup.py
src/whykay/__init__.py
src/whykay/config.py
src/whykay.egg-info/PKG-INFO
src/whykay.egg-info/SOURCES.txt
src/whykay.egg-info/dependency_links.txt
src/whykay.egg-info/requires.txt
src/whykay.egg-info/top_level.txt
src/whykay/helpers/__init__.py
src/whykay/helpers/git_history.py
src/whykay/helpers/logs.py
src/whykay/investments/__init__.py
src/whykay/investments/fetch_markets_data.py
src/whykay/investments/industry_analyzer.py
src/whykay/investments/stocks_analyzer.py