Metadata-Version: 2.1
Name: whykay
Version: 0.4.0
Summary: Python toolstack for helper functions and efficient connectivity
Home-page: https://github.com/yasir-khalid/whykay
Author: Yasir Khalid
Author-email: yasir_khalid@outlook.com
License: UNKNOWN
Download-URL: https://github.com/yasir-khalid/whykay
Platform: UNKNOWN
Classifier: Natural Language :: English
Classifier: Intended Audience :: Developers
Classifier: Intended Audience :: System Administrators
Classifier: License :: OSI Approved :: Apache Software License
Classifier: Programming Language :: Python :: 3 :: Only
Classifier: Programming Language :: Python :: 3.7
Classifier: Programming Language :: Python :: 3.8
Classifier: Programming Language :: Python :: 3.9
Classifier: Programming Language :: Python :: 3.10
Classifier: Programming Language :: Python :: 3.11
Classifier: Topic :: Software Development :: Libraries
Requires-Python: >=3.8
License-File: LICENSE
